README.md
setup.py
tunm_proto/__init__.py
tunm_proto/bytebuffer.py
tunm_proto/test_proto.py
tunm_proto/tunm.py
tunm_proto.egg-info/PKG-INFO
tunm_proto.egg-info/SOURCES.txt
tunm_proto.egg-info/dependency_links.txt
tunm_proto.egg-info/requires.txt
tunm_proto.egg-info/top_level.txt