Metadata-Version: 2.1
Name: tunm-proto
Version: 0.1.1
Summary: a binary proto like json
Home-page: UNKNOWN
Author: tickbh
Author-email: tickdream125@hotmail.com
License: MIT Licence
Keywords: tunm proto for Python
Platform: any
Requires-Python: >=3.6
Provides-Extra: extra
